odoo/addons/web_widget_one2many_product_picker/README.rst
odoo/addons/web_widget_one2many_product_picker/__init__.py
odoo/addons/web_widget_one2many_product_picker/__manifest__.py
odoo/addons/web_widget_one2many_product_picker/i18n/ca.po
odoo/addons/web_widget_one2many_product_picker/i18n/es.po
odoo/addons/web_widget_one2many_product_picker/i18n/pt_BR.po
odoo/addons/web_widget_one2many_product_picker/i18n/web_widget_one2many_product_picker.pot
odoo/addons/web_widget_one2many_product_picker/models/__init__.py
odoo/addons/web_widget_one2many_product_picker/models/base.py
odoo/addons/web_widget_one2many_product_picker/readme/CONFIGURE.rst
odoo/addons/web_widget_one2many_product_picker/readme/CONTRIBUTORS.rst
odoo/addons/web_widget_one2many_product_picker/readme/DESCRIPTION.rst
odoo/addons/web_widget_one2many_product_picker/readme/INSTALL.rst
odoo/addons/web_widget_one2many_product_picker/readme/ROADMAP.rst
odoo/addons/web_widget_one2many_product_picker/readme/USAGE.rst
odoo/addons/web_widget_one2many_product_picker/static/description/icon.png
odoo/addons/web_widget_one2many_product_picker/static/description/index.html
odoo/addons/web_widget_one2many_product_picker/static/img/product_picker.gif
odoo/addons/web_widget_one2many_product_picker/static/img/product_picker_anat.png
odoo/addons/web_widget_one2many_product_picker/static/src/js/tools.js
odoo/addons/web_widget_one2many_product_picker/static/src/js/views/basic_model.js
odoo/addons/web_widget_one2many_product_picker/static/src/js/views/form_controller.js
odoo/addons/web_widget_one2many_product_picker/static/src/js/views/form_renderer.js
odoo/addons/web_widget_one2many_product_picker/static/src/js/views/form_view.js
odoo/addons/web_widget_one2many_product_picker/static/src/js/views/One2ManyProductPicker/quick_create_form.js
odoo/addons/web_widget_one2many_product_picker/static/src/js/views/One2ManyProductPicker/quick_create_form_view.js
odoo13_addon_web_widget_one2many_product_picker-13.0.2.0.3.dist-info/METADATA
odoo13_addon_web_widget_one2many_product_picker-13.0.2.0.3.dist-info/WHEEL
odoo13_addon_web_widget_one2many_product_picker-13.0.2.0.3.dist-info/top_level.txt
odoo13_addon_web_widget_one2many_product_picker-13.0.2.0.3.dist-info/RECORD
