Metadata-Version: 2.1
Name: odoo13-addon-web-widget-one2many-product-picker
Version: 13.0.2.0.3
Summary: Widget to select products on one2many fields
Home-page: https://github.com/OCA/web
Author: Tecnativa, Odoo Community Association (OCA)
Author-email: support@odoo-community.org
License: AGPL-3
Platform: UNKNOWN
Classifier: Programming Language :: Python
Classifier: Framework :: Odoo
Classifier: Framework :: Odoo :: 13.0
Classifier: License :: OSI Approved :: GNU Affero General Public License v3
Requires-Python: >=3.5
Requires-Dist: odoo (<13.1dev,>=13.0a)
